setup.py
scramble/__init__.py
scramble/scrambleText.py
scramble.egg-info/PKG-INFO
scramble.egg-info/SOURCES.txt
scramble.egg-info/dependency_links.txt
scramble.egg-info/top_level.txt