Metadata-Version: 1.1
Name: scramble
Version: 1.0
Summary: A library for scrambling streams of text.
Home-page: https://github.com/nikkisquared/scramble
Author: Nikki
Author-email: private
License: UNKNOWN
Keywords: random text scramble
Platform: UNKNOWN
Classifier: Development Status :: 5 - Production/Stable
Classifier: Environment :: Win32 (MS Windows)
Classifier: Environment :: MacOS X
Classifier: Environment :: X11 Applications
Classifier: Intended Audience :: Developers
Classifier: Intended Audience :: End Users/Desktop
Classifier: Operating System :: OS Independent
Classifier: Programming Language :: Python
Classifier: Programming Language :: Python :: 2
Classifier: Programming Language :: Python :: 2.7
Classifier: Topic :: Artistic Software
Classifier: Topic :: Text Processing
Classifier: Topic :: Utilities
